fewerbytes/__init__.py
fewerbytes/compression_details.py
fewerbytes/exceptions.py
fewerbytes/integer_compression.py
fewerbytes/integer_decompression.py
fewerbytes/types.py
fewerbytes-0.0.1.dist-info/METADATA
fewerbytes-0.0.1.dist-info/RECORD
fewerbytes-0.0.1.dist-info/WHEEL
fewerbytes-0.0.1.dist-info/top_level.txt
