Metadata-Version: 2.1
Name: fewerbytes
Version: 0.0.1
Summary: Compression techniques for numpy arrays
Home-page: https://github.com/briankopp/fewerbytes
Author: Brian Kopp
Author-email: briankopp.usa@gmail.com
License: UNKNOWN
Platform: UNKNOWN
Requires-Dist: numpy
